Stkml/Cli.py
Stkml/Utils.py
Stkml/__init__.py
Stkml/Diagram/__init__.py
Stkml/Diagram/Graphviz/GraphvizManger.py
Stkml/Diagram/Graphviz/Layer.py
Stkml/Diagram/Graphviz/LayerDiagram.py
Stkml/Diagram/Graphviz/Node.py
Stkml/Diagram/Graphviz/RegionDiagram.py
Stkml/Diagram/Graphviz/SystemDiagram.py
Stkml/Diagram/Graphviz/__init__.py
Stkml/Diagram/Map/NodeMarker.py
Stkml/Diagram/Map/RegionNotFound.py
Stkml/Diagram/Map/TopologyMap.py
Stkml/Diagram/Map/__init__.py
Stkml/Drawio/Component.py
Stkml/Drawio/Layer.py
Stkml/Drawio/Link.py
Stkml/Drawio/Node.py
Stkml/Drawio/Tier.py
Stkml/Drawio/__init__.py
Stkml/Stkml/Link.py
Stkml/Stkml/ModelException.py
Stkml/Stkml/Node.py
Stkml/Stkml/Region.py
Stkml/Stkml/StkmlSyntaxicError.py
Stkml/Stkml/StkmlSyntaxicErrorList.py
Stkml/Stkml/Tier.py
Stkml/Stkml/Topology.py
Stkml/Stkml/WarningList.py
Stkml/Stkml/__init__.py
Stkml/Stkml/LayerElement/BusinesslayerElement.py
Stkml/Stkml/LayerElement/ConnectivitylayerElement.py
Stkml/Stkml/LayerElement/DatalayerElement.py
Stkml/Stkml/LayerElement/EnergylayerElement.py
Stkml/Stkml/LayerElement/MessaginglayerElement.py
Stkml/Stkml/LayerElement/NetworklayerElement.py
Stkml/Stkml/LayerElement/PhysicallayerElement.py
Stkml/Stkml/LayerElement/ServicelayerElement.py
Stkml/Stkml/LayerElement/__init__.py
Stkml/Stkml/LayerElement/Component/BusinessComponent.py
Stkml/Stkml/LayerElement/Component/EnergyComponent.py
Stkml/Stkml/LayerElement/Component/NetworkComponent.py
Stkml/Stkml/LayerElement/Component/PhysicalComponent.py
Stkml/Stkml/LayerElement/Component/__init__.py
Stkml/Stkml/LayerElement/Component/DataComponent/Arg.py
Stkml/Stkml/LayerElement/Component/DataComponent/Data.py
Stkml/Stkml/LayerElement/Component/DataComponent/Job.py
Stkml/Stkml/LayerElement/Component/DataComponent/__init__.py
Stkml/Stkml/LayerElement/Component/MessagingComponent/Message.py
Stkml/Stkml/LayerElement/Component/MessagingComponent/__init__.py
Stkml/templates/StkmlIn/StkMl.yaml.j2
Stkml/templates/diagram/resources/Application.png
stkml-1.0.2.dist-info/LICENSE
stkml-1.0.2.dist-info/METADATA
stkml-1.0.2.dist-info/WHEEL
stkml-1.0.2.dist-info/entry_points.txt
stkml-1.0.2.dist-info/top_level.txt
stkml-1.0.2.dist-info/RECORD
