Metadata-Version: 2.1
Name: stkml
Version: 1.0.2
Summary: stkml is a transpiler for stckml language to generate output for different backend as diagram, drawio, map.
Home-page: https://stkml.stackeo.io/
Author: Fraoui Zakaria
Author-email: zakaria@stackeo.io
License: GNU Affero General Public License v3
Platform: UNKNOWN
Classifier: Programming Language :: Python :: 3.6
Classifier: License :: OSI Approved :: GNU Affero General Public License v3
Classifier: Operating System :: OS Independent
Classifier: Intended Audience :: Developers
Classifier: Environment :: Console
Requires-Dist: click
Requires-Dist: decorator
Requires-Dist: diagrams
Requires-Dist: folium
Requires-Dist: geopy
Requires-Dist: Jinja2
Requires-Dist: jsonschema
Requires-Dist: Pillow
Requires-Dist: pyyaml
Provides-Extra: dev
Requires-Dist: pylint ; extra == 'dev'
Requires-Dist: coverage ; extra == 'dev'
Requires-Dist: tox ; extra == 'dev'
Requires-Dist: twine ; extra == 'dev'
